pypkgs_crh/__init__.py
pypkgs_crh/pypkgs_crh.py
pypkgs_crh-0.1.0.dist-info/LICENSE
pypkgs_crh-0.1.0.dist-info/WHEEL
pypkgs_crh-0.1.0.dist-info/METADATA
pypkgs_crh-0.1.0.dist-info/RECORD
