Metadata-Version: 2.1
Name: pypkgs-crh
Version: 0.1.0
Summary: Python package for individual assignment 1 of dsci 524
License: MIT
Author: Cameron Harris
Author-email: camharris22@gmail.com
Requires-Python: >=3.8,<4.0
Classifier: License :: OSI Approved :: MIT License
Classifier: Programming Language :: Python :: 3
Classifier: Programming Language :: Python :: 3.8
Classifier: Programming Language :: Python :: 3.9
Requires-Dist: pandas (>=1.2.2,<2.0.0)
